sentry_tryton.py
sentry_tryton-0.7.dist-info/LICENSE
sentry_tryton-0.7.dist-info/METADATA
sentry_tryton-0.7.dist-info/WHEEL
sentry_tryton-0.7.dist-info/top_level.txt
sentry_tryton-0.7.dist-info/RECORD
