Metadata-Version: 2.1
Name: sentry_tryton
Version: 0.7
Summary: Sentry Integration for the Tryton Framework
Home-page: https://gitlab.com/pokoli/sentry-tryton/
Author: Sergi Almacellas Abellana
Author-email: sergi@kopen.es
License: GPL-3
Keywords: sentry tryton
Platform: any
Classifier: Framework :: Tryton
Classifier: Intended Audience :: Developers
Classifier: License :: OSI Approved :: GNU General Public License v3 or later (GPLv3+)
Classifier: Operating System :: OS Independent
Classifier: Programming Language :: Python :: 3.8
Classifier: Programming Language :: Python :: 3.9
Classifier: Programming Language :: Python :: 3.10
Classifier: Programming Language :: Python :: 3.11
Classifier: Programming Language :: Python :: 3.12
Classifier: Topic :: Software Development :: Libraries :: Python Modules
Requires-Python: >=3.5
License-File: LICENSE
Requires-Dist: raven
Requires-Dist: trytond >=4.2
